wtisdk/__init__.py
wtisdk/wtisdk.py
wtisdk/tests/__init__.py
wtisdk/tests/test_wtisdk.py
wtisdk-1.5.7.dist-info/LICENSE
wtisdk-1.5.7.dist-info/METADATA
wtisdk-1.5.7.dist-info/WHEEL
wtisdk-1.5.7.dist-info/top_level.txt
wtisdk-1.5.7.dist-info/RECORD
